tpy357/__init__.py
tpy357/__main__.py
tpy357/cli.py
tpy357-1.1.0.dist-info/LICENSE
tpy357-1.1.0.dist-info/METADATA
tpy357-1.1.0.dist-info/WHEEL
tpy357-1.1.0.dist-info/entry_points.txt
tpy357-1.1.0.dist-info/top_level.txt
tpy357-1.1.0.dist-info/RECORD
