Metadata-Version: 2.1
Name: tpy357
Version: 1.1.0
Summary: ThermoPro TP357 Bluetooth Python Library
Author-email: Alex Pacini <alexpacini90@gmail.com>
Project-URL: Homepage, https://gitlab.com/alexpacini/tpy357
Project-URL: Issues, https://gitlab.com/alexpacini/tpy357/-/issues
Classifier: Programming Language :: Python :: 3
Classifier: Intended Audience :: Developers
Classifier: Natural Language :: English
Requires-Python: >=3.10
License-File: LICENSE
Requires-Dist: bleak
Requires-Dist: tomli
Requires-Dist: pandas
Requires-Dist: matplotlib
